{
	"RemapUnityFiles": 
	{
		"Module.PlayFab.1_of_4.cpp.obj": [
			"PlayFab.cpp.obj",
			"PlayFabAdminAPI.cpp.obj",
			"PlayFabAdminModelDecoder.cpp.obj",
			"PlayFabAdminModels.cpp.obj",
			"PlayFabAuthenticationAPI.cpp.obj",
			"PlayFabAuthenticationModelDecoder.cpp.obj",
			"PlayFabAuthenticationModels.cpp.obj",
			"PlayFabBaseModel.cpp.obj",
			"PlayFabClientAPI.cpp.obj"
		],
		"Module.PlayFab.2_of_4.cpp.obj": [
			"PlayFabClientModelDecoder.cpp.obj",
			"PlayFabClientModels.cpp.obj",
			"PlayFabCloudScriptAPI.cpp.obj",
			"PlayFabCloudScriptModelDecoder.cpp.obj",
			"PlayFabCloudScriptModels.cpp.obj",
			"PlayFabDataAPI.cpp.obj",
			"PlayFabDataModelDecoder.cpp.obj",
			"PlayFabDataModels.cpp.obj",
			"PlayFabEventsAPI.cpp.obj",
			"PlayFabEventsModelDecoder.cpp.obj",
			"PlayFabEventsModels.cpp.obj",
			"PlayFabExperimentationAPI.cpp.obj",
			"PlayFabExperimentationModelDecoder.cpp.obj",
			"PlayFabExperimentationModels.cpp.obj",
			"PlayFabGroupsAPI.cpp.obj",
			"PlayFabGroupsModelDecoder.cpp.obj",
			"PlayFabGroupsModels.cpp.obj",
			"PlayFabInsightsAPI.cpp.obj",
			"PlayFabInsightsModelDecoder.cpp.obj",
			"PlayFabInsightsModels.cpp.obj",
			"PlayFabJsonObject.cpp.obj",
			"PlayFabJsonValue.cpp.obj",
			"PlayFabLocalizationAPI.cpp.obj",
			"PlayFabLocalizationModelDecoder.cpp.obj",
			"PlayFabLocalizationModels.cpp.obj",
			"PlayFabMatchmakerAPI.cpp.obj",
			"PlayFabMatchmakerModelDecoder.cpp.obj",
			"PlayFabMatchmakerModels.cpp.obj",
			"PlayFabMultiplayerAPI.cpp.obj"
		],
		"Module.PlayFab.3_of_4.cpp.obj": [
			"PlayFabMultiplayerModelDecoder.cpp.obj",
			"PlayFabMultiplayerModels.cpp.obj",
			"PlayFabProfilesAPI.cpp.obj",
			"PlayFabProfilesModelDecoder.cpp.obj",
			"PlayFabProfilesModels.cpp.obj",
			"PlayFabServerAPI.cpp.obj"
		],
		"Module.PlayFab.4_of_4.cpp.obj": [
			"PlayFabServerModelDecoder.cpp.obj",
			"PlayFabServerModels.cpp.obj",
			"PlayFabUtilities.cpp.obj"
		],
		"Module.PlayFab.gen.1_of_18.cpp.obj": [
			"PlayFab.init.gen.cpp.obj",
			"PlayFabAdminAPI.gen.cpp.obj"
		],
		"Module.PlayFab.gen.2_of_18.cpp.obj": [
			"PlayFabAdminModelDecoder.gen.cpp.obj"
		],
		"Module.PlayFab.gen.3_of_18.cpp.obj": [
			"PlayFabAdminModels.gen.cpp.obj"
		],
		"Module.PlayFab.gen.4_of_18.cpp.obj": [
			"PlayFabAuthenticationAPI.gen.cpp.obj",
			"PlayFabAuthenticationModelDecoder.gen.cpp.obj",
			"PlayFabAuthenticationModels.gen.cpp.obj",
			"PlayFabBaseModel.gen.cpp.obj",
			"PlayFabClientAPI.gen.cpp.obj"
		],
		"Module.PlayFab.gen.5_of_18.cpp.obj": [
			"PlayFabClientModelDecoder.gen.cpp.obj"
		],
		"Module.PlayFab.gen.6_of_18.cpp.obj": [
			"PlayFabClientModels.gen.cpp.obj"
		],
		"Module.PlayFab.gen.7_of_18.cpp.obj": [
			"PlayFabCloudScriptAPI.gen.cpp.obj",
			"PlayFabCloudScriptModelDecoder.gen.cpp.obj",
			"PlayFabCloudScriptModels.gen.cpp.obj"
		],
		"Module.PlayFab.gen.8_of_18.cpp.obj": [
			"PlayFabDataAPI.gen.cpp.obj",
			"PlayFabDataModelDecoder.gen.cpp.obj",
			"PlayFabDataModels.gen.cpp.obj",
			"PlayFabEnums.gen.cpp.obj"
		],
		"Module.PlayFab.gen.9_of_18.cpp.obj": [
			"PlayFabEventsAPI.gen.cpp.obj",
			"PlayFabEventsModelDecoder.gen.cpp.obj",
			"PlayFabEventsModels.gen.cpp.obj",
			"PlayFabExperimentationAPI.gen.cpp.obj",
			"PlayFabExperimentationModelDecoder.gen.cpp.obj",
			"PlayFabExperimentationModels.gen.cpp.obj"
		],
		"Module.PlayFab.gen.10_of_18.cpp.obj": [
			"PlayFabGroupsAPI.gen.cpp.obj"
		],
		"Module.PlayFab.gen.11_of_18.cpp.obj": [
			"PlayFabGroupsModelDecoder.gen.cpp.obj",
			"PlayFabGroupsModels.gen.cpp.obj"
		],
		"Module.PlayFab.gen.12_of_18.cpp.obj": [
			"PlayFabInsightsAPI.gen.cpp.obj",
			"PlayFabInsightsModelDecoder.gen.cpp.obj",
			"PlayFabInsightsModels.gen.cpp.obj",
			"PlayFabJsonObject.gen.cpp.obj",
			"PlayFabJsonValue.gen.cpp.obj"
		],
		"Module.PlayFab.gen.13_of_18.cpp.obj": [
			"PlayFabLocalizationAPI.gen.cpp.obj",
			"PlayFabLocalizationModelDecoder.gen.cpp.obj",
			"PlayFabLocalizationModels.gen.cpp.obj",
			"PlayFabLoginResultCommon.gen.cpp.obj",
			"PlayFabMatchmakerAPI.gen.cpp.obj",
			"PlayFabMatchmakerModelDecoder.gen.cpp.obj",
			"PlayFabMatchmakerModels.gen.cpp.obj",
			"PlayFabMultiplayerAPI.gen.cpp.obj"
		],
		"Module.PlayFab.gen.14_of_18.cpp.obj": [
			"PlayFabMultiplayerModelDecoder.gen.cpp.obj",
			"PlayFabMultiplayerModels.gen.cpp.obj"
		],
		"Module.PlayFab.gen.15_of_18.cpp.obj": [
			"PlayFabProfilesAPI.gen.cpp.obj",
			"PlayFabProfilesModelDecoder.gen.cpp.obj",
			"PlayFabProfilesModels.gen.cpp.obj",
			"PlayFabRequestCommon.gen.cpp.obj",
			"PlayFabResultCommon.gen.cpp.obj",
			"PlayFabServerAPI.gen.cpp.obj"
		],
		"Module.PlayFab.gen.16_of_18.cpp.obj": [
			"PlayFabServerModelDecoder.gen.cpp.obj"
		],
		"Module.PlayFab.gen.17_of_18.cpp.obj": [
			"PlayFabServerModels.gen.cpp.obj"
		],
		"Module.PlayFab.gen.18_of_18.cpp.obj": [
			"PlayFabUtilities.gen.cpp.obj"
		]
	}
}